CfgGenerator.py
ComputeCostFunctions.py
OptiPRISMS.py
__init__.py
costFunctions.py
misor.py
triangulate.py
vtk_utils.py
OptiPRISMS-1.1.1.dist-info/LICENSE
OptiPRISMS-1.1.1.dist-info/METADATA
OptiPRISMS-1.1.1.dist-info/WHEEL
OptiPRISMS-1.1.1.dist-info/top_level.txt
OptiPRISMS-1.1.1.dist-info/RECORD
