Metadata-Version: 2.1
Name: OptiPRISMS
Version: 1.1.1
Summary: Identifies Crystal Plasticity (CP) parameters by inverse analysis based on CPFEM simulations performed using PRISMS-Plasticity
Home-page: https://github.com/DorianDepriester/OptiPRISMS
Author: Dorian Depriester
Author-email: dorian.depriester@ensam.eu
License: GNU Lesser General Public License v2.1
License-File: LICENSE
Requires-Dist: scipy
Requires-Dist: numpy
Requires-Dist: vtk
Requires-Dist: pandas
Requires-Dist: optimparallel
